minepython/__init__.py
minepython/__init__.pyi
minepython/block.cp38-win_amd64.pyd
minepython/connection.cp38-win_amd64.pyd
minepython/event.cp38-win_amd64.pyd
minepython/keyhandle.cp38-win_amd64.pyd
minepython/minecollection.py
minepython/minecraft.cp38-win_amd64.pyd
minepython/minecraft.pyi
minepython/util.cp38-win_amd64.pyd
minepython/vec3.cp38-win_amd64.pyd
minepython/verifysign.cp38-win_amd64.pyd
minepython-0.0.5.dist-info/METADATA
minepython-0.0.5.dist-info/WHEEL
minepython-0.0.5.dist-info/top_level.txt
minepython-0.0.5.dist-info/RECORD
