Metadata-Version: 2.1
Name: minepython
Version: 0.0.5
Summary: 在Minecraft游戏环境中学习编程，使用编程的方式来玩Minecraft
Home-page: http://www.minepython.com
Author: QinBingFeng
Author-email: 114479602@qq.com
License: UNKNOWN
Platform: UNKNOWN
